{
    "data": {
        "Javascript": [
            {
                "id": 1,
                "name": "ES6语法实战",
                "img": "LearnES6_Final.png",
                "price": "100",
                "solded": "561",
                "tag": "Javascript"
            },
            {
                "id": 2,
                "name": "Typescript实战",
                "img": "Typescript_Plumbing_image.png",
                "price": "100",
                "solded": "156",
                "tag": "Javascript"
            },
            {
                "id": 3,
                "name": "Javascript算法实战",
                "img": "JSBasic-Algorithms_Final.png",
                "price": "100",
                "solded": "526",
                "tag": "Javascript"
            }
        ],
        "React": [
            {
                "id": 4,
                "name": "React入门",
                "img": "ReactBeginners.png",
                "price": "100",
                "solded": "536",
                "tag": "React"
            },
            {
                "id": 5,
                "name": "ReactNative开发自己的APP",
                "img": "ReactNative.png",
                "price": "100",
                "solded": "456",
                "tag": "React"
            },
            {
                "id": 6,
                "name": "React服务端渲染实战",
                "img": "ReactNextServer_Final.png",
                "price": "100",
                "solded": "556",
                "tag": "React"
            },
            {
                "id": 7,
                "name": "Redux Sage中间件实战",
                "img": "ReduxSaga.png",
                "price": "100",
                "solded": "2256",
                "tag": "React"
            },
            {
                "id": 8,
                "name": "试用react开发PWA应用",
                "img": "PWAReact_Final.png",
                "price": "100",
                "solded": "1156",
                "tag": "React"
            },
            {
                "id": 9,
                "name": "React Hooks实战",
                "img": "SimplifyHooks_Final.png",
                "price": "100",
                "solded": "5361",
                "tag": "React"
            },
            {
                "id": 10,
                "name": "React Mobx状态管理实战",
                "img": "React_Mobx_TS.png",
                "price": "100",
                "solded": "956",
                "tag": "React"
            }
        ],
        "Vuejs": [
            {
                "id": 11,
                "name": "Vue进阶实战",
                "img": "VueJS_Final.png",
                "price": "180",
                "solded": "586",
                "tag": "Vuejs"
            },
            {
                "id": 12,
                "name": "Vuejs开发pwa应用",
                "img": "VuePwa.png",
                "price": "100",
                "solded": "596",
                "tag": "Vuejs"
            },
            {
                "id": 13,
                "name": "试用TS开发Vuejs应用",
                "img": "TSVue_Final.png",
                "price": "100",
                "solded": "526",
                "tag": "Vuejs"
            }
        ],
        "Git": [
            {
                "id": 14,
                "name": "Github从入门到精通",
                "img": "github.png",
                "price": "99",
                "solded": "10",
                "tag": "Git"
            },
            {
                "id": 15,
                "name": "Git版本控制实战",
                "img": "LearnGit.png",
                "price": "49",
                "solded": "180",
                "tag": "Git"
            }
        ],
        "Test": [
            {
                "id": 16,
                "name": "Puppetee测试入门",
                "img": "TestGooglePuppeteer_Final.png",
                "price": "10",
                "solded": "56",
                "tag": "Test"
            },
            {
                "id": 17,
                "name": "使用jest测试你的React项目",
                "img": "TestReactJest.png",
                "price": "30",
                "solded": "10",
                "tag": "Test"
            }
        ],
        "Python": [
            {
                "id": 18,
                "name": "Python从入门到精通",
                "img": "IntroPython.png",
                "price": "100",
                "solded": "56",
                "tag": "Python"
            }
        ],
        "Node.js": [
            {
                "id": 19,
                "name": "使用Docker部署你的nodejs",
                "img": "NodeDocker_1000.png",
                "price": "100",
                "solded": "56",
                "tag": "Node.js"
            },
            {
                "id": 20,
                "name": "在AWS环境部署nodejs",
                "img": "NodeAWSServerless_Final.png",
                "price": "100",
                "solded": "56",
                "tag": "Node.js"
            }
        ],
        "GraphQL": [
            {
                "id": 21,
                "name": "GraphQL从入门到精通",
                "img": "GraphQL_Final.png",
                "price": "100",
                "solded": "56",
                "tag": "GraphQL"
            }
        ]
    },
    "tags": [
        "Javascript",
        "React",
        "Vuejs",
        "Git",
        "Test",
        "Python",
        "Node.js",
        "GraphQL"
    ]
}